xstampp_model_parser/__init__.py
xstampp_model_parser/hazx_parser/__init__.py
xstampp_model_parser/hazx_parser/hazx_parser.py
xstampp_model_parser/hazx_parser/models.py
xstampp_model_parser-0.1.0.dist-info/METADATA
xstampp_model_parser-0.1.0.dist-info/WHEEL
xstampp_model_parser-0.1.0.dist-info/top_level.txt
xstampp_model_parser-0.1.0.dist-info/RECORD
